speedup_work_lib/__init__.py
speedup_work_lib/file_tool.py
speedup_work_lib/simple_log.py
speedup_work_lib/ssh_client.py
speedup_work_lib-0.3.2.dist-info/LICENSE
speedup_work_lib-0.3.2.dist-info/METADATA
speedup_work_lib-0.3.2.dist-info/WHEEL
speedup_work_lib-0.3.2.dist-info/top_level.txt
speedup_work_lib-0.3.2.dist-info/RECORD
