Metadata-Version: 2.1
Name: speedup-work-lib
Version: 0.3.2
Summary: A Python library to speed up work
Home-page: https://github.com/mndarren/Speedup-Work-Lib.git
Author: Darren Xie
Author-email: mndarren@gmail.com
License: Apache
Platform: UNKNOWN
Classifier: Programming Language :: Python :: 3
Classifier: Programming Language :: Python :: 3.9
License-File: LICENSE
Requires-Dist: paramiko
